<?xml version="1.0" encoding="UTF-8"?>
<bpmn:definitions xmlns:xsi="http://www.w3.org/2001/XMLSchema-instance" xmlns:bpmn="http://www.omg.org/spec/BPMN/20100524/MODEL" xmlns:bpmndi="http://www.omg.org/spec/BPMN/20100524/DI" xmlns:dc="http://www.omg.org/spec/DD/20100524/DC" xmlns:di="http://www.omg.org/spec/DD/20100524/DI" id="Definitions_0bgt5xh" targetNamespace="http://bpmn.io/schema/bpmn">
  <bpmn:process id="Process_1" isExecutable="true">
    <bpmn:startEvent id="StartEvent_1">
      <bpmn:outgoing>SequenceFlow_1x1hkyk</bpmn:outgoing>
    </bpmn:startEvent>
    <bpmn:task id="Task_190fvvu" name="用户任务A">
      <bpmn:incoming>SequenceFlow_1x1hkyk</bpmn:incoming>
      <bpmn:outgoing>SequenceFlow_16jem52</bpmn:outgoing>
    </bpmn:task>
    <bpmn:sequenceFlow id="SequenceFlow_1x1hkyk" sourceRef="StartEvent_1" targetRef="Task_190fvvu" />
    <bpmn:endEvent id="EndEvent_0csr88t">
      <bpmn:incoming>SequenceFlow_16jem52</bpmn:incoming>
    </bpmn:endEvent>
    <bpmn:sequenceFlow id="SequenceFlow_16jem52" sourceRef="Task_190fvvu" targetRef="EndEvent_0csr88t" />
  </bpmn:process>
  <bpmndi:BPMNDiagram id="BPMNDiagram_1">
    <bpmndi:BPMNPlane id="BPMNPlane_1" bpmnElement="Process_1">
      <bpmndi:BPMNShape id="_BPMNShape_StartEvent_2" bpmnElement="StartEvent_1">
        <dc:Bounds x="173" y="102" width="36" height="36" />
      </bpmndi:BPMNShape>
      <bpmndi:BPMNShape id="Task_190fvvu_di" bpmnElement="Task_190fvvu">
        <dc:Bounds x="259" y="80" width="100" height="80" />
      </bpmndi:BPMNShape>
      <bpmndi:BPMNEdge id="SequenceFlow_1x1hkyk_di" bpmnElement="SequenceFlow_1x1hkyk">
        <di:waypoint x="209" y="120" />
        <di:waypoint x="259" y="120" />
      </bpmndi:BPMNEdge>
      <bpmndi:BPMNShape id="EndEvent_0csr88t_di" bpmnElement="EndEvent_0csr88t">
        <dc:Bounds x="409" y="102" width="36" height="36" />
      </bpmndi:BPMNShape>
      <bpmndi:BPMNEdge id="SequenceFlow_16jem52_di" bpmnElement="SequenceFlow_16jem52">
        <di:waypoint x="359" y="120" />
        <di:waypoint x="409" y="120" />
      </bpmndi:BPMNEdge>
    </bpmndi:BPMNPlane>
  </bpmndi:BPMNDiagram>
</bpmn:definitions>
